bayesian_mab/VERSION
bayesian_mab/__init__.py
bayesian_mab/arm.py
bayesian_mab/finisher.py
bayesian_mab/models.py
bayesian_mab/multi_armed_bandit.py
bayesian_mab/reward.py
bayesian_mab/tracker.py
bayesian_mab/contrib/__init__.py
bayesian_mab/contrib/calc_bayesian_prob.py
bayesian_mab/contrib/logger.py
bayesian_mab-0.1.0.data/data/VERSION
bayesian_mab-0.1.0.dist-info/LICENSE
bayesian_mab-0.1.0.dist-info/METADATA
bayesian_mab-0.1.0.dist-info/WHEEL
bayesian_mab-0.1.0.dist-info/top_level.txt
bayesian_mab-0.1.0.dist-info/RECORD
