Metadata-Version: 2.1
Name: bayesian-mab
Version: 0.1.0
Summary: Bayesian Multi Armed Bandit
Home-page: https://github.com/modestobr/bayesian_multi_armed_bandit
Author: Brandao, Iago M.
Keywords: Bayesian Inference,Multi Armed Bandit,Reinforcement Learning,Website optimization,A/B Testing,Online Advertising
Classifier: Programming Language :: Python :: 3
Classifier: License :: OSI Approved :: MIT License
Classifier: Operating System :: OS Independent
Classifier: Development Status :: 1 - Planning
Requires-Python: >=3.8
License-File: LICENSE
Requires-Dist: tqdm ==4.66.1
Requires-Dist: python-dotenv ==1.0.0
Requires-Dist: numpy ==1.25.2
Requires-Dist: pandas ==1.5.3
Requires-Dist: openpyxl ==3.1.2
Requires-Dist: seaborn ==0.13.0
Requires-Dist: scikit-learn ==1.2.2
Requires-Dist: pydantic ==2.5.2
Requires-Dist: names ==0.3.0
Requires-Dist: numba ==0.58.1
